pybex/__init__.py
pybex/__main__.py
pybex/builtins.py
pybex/classes.py
pybex/interpreter.py
pybex/parser.py
pybex/run.py
pybex-0.0.2.dist-info/LICENSE
pybex-0.0.2.dist-info/METADATA
pybex-0.0.2.dist-info/WHEEL
pybex-0.0.2.dist-info/top_level.txt
pybex-0.0.2.dist-info/RECORD
